italia-0.4.0.dist-info/METADATA
italia-0.4.0.dist-info/WHEEL
italia-0.4.0.dist-info/licenses/LICENCE
italia/__init__.py
italia/story.py
italia/team.py
italia-0.4.0.dist-info/RECORD
