Metadata-Version: 2.1
Name: italia
Version: 0.4.0
Summary: A fun package celebrating the Python Italia association and PyCon Italia
Author-Email: Python Italia <help@pycon.it>
License: MIT
Requires-Python: >=3.8
